MANIFEST.in
README
setup.py
tmux_master.py
tmux_master.egg-info/PKG-INFO
tmux_master.egg-info/SOURCES.txt
tmux_master.egg-info/dependency_links.txt
tmux_master.egg-info/entry_points.txt
tmux_master.egg-info/requires.txt
tmux_master.egg-info/top_level.txt