Metadata-Version: 1.1
Name: tmux-master
Version: 0.0
Summary: A tool that runs a master tmux session to control slave tmux sessions on the specified hosts
Home-page: https://github.com/KonishchevDmitry/tmux-master
Author: Dmitry Konishchev
Author-email: konishchev@gmail.com
License: GPL
Platform: unix
Platform: linux
Platform: osx
Classifier: Development Status :: 3 - Alpha
Classifier: Environment :: Console
Classifier: Intended Audience :: Developers
Classifier: Intended Audience :: System Administrators
Classifier: License :: OSI Approved :: GNU General Public License v3 (GPLv3)
Classifier: Operating System :: MacOS :: MacOS X
Classifier: Operating System :: POSIX
Classifier: Operating System :: Unix
Classifier: Programming Language :: Python :: 2
Classifier: Programming Language :: Python :: 3
Classifier: Topic :: System :: Shells
Classifier: Topic :: System :: Systems Administration
Classifier: Topic :: Terminals
Classifier: Topic :: Utilities
